bloky/__init__.py
bloky/main.py
bloky-0.1.1.dist-info/WHEEL
bloky-0.1.1.dist-info/entry_points.txt
bloky-0.1.1.dist-info/METADATA
bloky-0.1.1.dist-info/RECORD
