Metadata-Version: 2.3
Name: bloky
Version: 0.1.1
Summary: Analyzes Python code to detect blocking operations
Requires-Python: >=3.10
